{
	"textures": [
		{
			"image": "roads.png",
			"format": "RGBA8888",
			"size": {
				"w": 352,
				"h": 32
			},
			"scale": 1,
			"frames": [
				{
					"filename": "0.png",
					"rotated": false,
					"trimmed": false,
					"sourceSize": {
						"w": 32,
						"h": 32
					},
					"spriteSourceSize": {
						"x": 0,
						"y": 0,
						"w": 32,
						"h": 32
					},
					"frame": {
						"x": 0,
						"y": 0,
						"w": 32,
						"h": 32
					},
					"anchor": {
						"x": 0.5,
						"y": 0.5
					}
				},
				{
					"filename": "1.png",
					"rotated": false,
					"trimmed": false,
					"sourceSize": {
						"w": 32,
						"h": 32
					},
					"spriteSourceSize": {
						"x": 0,
						"y": 0,
						"w": 32,
						"h": 32
					},
					"frame": {
						"x": 32,
						"y": 0,
						"w": 32,
						"h": 32
					},
					"anchor": {
						"x": 0.5,
						"y": 0.5
					}
				},
				{
					"filename": "2.png",
					"rotated": false,
					"trimmed": false,
					"sourceSize": {
						"w": 32,
						"h": 32
					},
					"spriteSourceSize": {
						"x": 0,
						"y": 0,
						"w": 32,
						"h": 32
					},
					"frame": {
						"x": 64,
						"y": 0,
						"w": 32,
						"h": 32
					},
					"anchor": {
						"x": 0.5,
						"y": 0.5
					}
				},
				{
					"filename": "3.png",
					"rotated": false,
					"trimmed": false,
					"sourceSize": {
						"w": 32,
						"h": 32
					},
					"spriteSourceSize": {
						"x": 0,
						"y": 0,
						"w": 32,
						"h": 32
					},
					"frame": {
						"x": 96,
						"y": 0,
						"w": 32,
						"h": 32
					},
					"anchor": {
						"x": 0.5,
						"y": 0.5
					}
				},
				{
					"filename": "4.png",
					"rotated": false,
					"trimmed": false,
					"sourceSize": {
						"w": 32,
						"h": 32
					},
					"spriteSourceSize": {
						"x": 0,
						"y": 0,
						"w": 32,
						"h": 32
					},
					"frame": {
						"x": 128,
						"y": 0,
						"w": 32,
						"h": 32
					},
					"anchor": {
						"x": 0.5,
						"y": 0.5
					}
				},
				{
					"filename": "5.png",
					"rotated": false,
					"trimmed": false,
					"sourceSize": {
						"w": 32,
						"h": 32
					},
					"spriteSourceSize": {
						"x": 0,
						"y": 0,
						"w": 32,
						"h": 32
					},
					"frame": {
						"x": 160,
						"y": 0,
						"w": 32,
						"h": 32
					},
					"anchor": {
						"x": 0.5,
						"y": 0.5
					}
				},
				{
					"filename": "6.png",
					"rotated": false,
					"trimmed": false,
					"sourceSize": {
						"w": 32,
						"h": 32
					},
					"spriteSourceSize": {
						"x": 0,
						"y": 0,
						"w": 32,
						"h": 32
					},
					"frame": {
						"x": 192,
						"y": 0,
						"w": 32,
						"h": 32
					},
					"anchor": {
						"x": 0.5,
						"y": 0.5
					}
				},
				{
					"filename": "7.png",
					"rotated": false,
					"trimmed": false,
					"sourceSize": {
						"w": 32,
						"h": 32
					},
					"spriteSourceSize": {
						"x": 0,
						"y": 0,
						"w": 32,
						"h": 32
					},
					"frame": {
						"x": 224,
						"y": 0,
						"w": 32,
						"h": 32
					},
					"anchor": {
						"x": 0.5,
						"y": 0.5
					}
				},
				{
					"filename": "8.png",
					"rotated": false,
					"trimmed": false,
					"sourceSize": {
						"w": 32,
						"h": 32
					},
					"spriteSourceSize": {
						"x": 0,
						"y": 0,
						"w": 32,
						"h": 32
					},
					"frame": {
						"x": 256,
						"y": 0,
						"w": 32,
						"h": 32
					},
					"anchor": {
						"x": 0.5,
						"y": 0.5
					}
				},
				{
					"filename": "9.png",
					"rotated": false,
					"trimmed": false,
					"sourceSize": {
						"w": 32,
						"h": 32
					},
					"spriteSourceSize": {
						"x": 0,
						"y": 0,
						"w": 32,
						"h": 32
					},
					"frame": {
						"x": 288,
						"y": 0,
						"w": 32,
						"h": 32
					},
					"anchor": {
						"x": 0.5,
						"y": 0.5
					}
				},
				{
					"filename": "10.png",
					"rotated": false,
					"trimmed": false,
					"sourceSize": {
						"w": 32,
						"h": 32
					},
					"spriteSourceSize": {
						"x": 0,
						"y": 0,
						"w": 32,
						"h": 32
					},
					"frame": {
						"x": 320,
						"y": 0,
						"w": 32,
						"h": 32
					},
					"anchor": {
						"x": 0.5,
						"y": 0.5
					}
				}
			]
		}
	],
	"meta": {
		"app": "https://www.codeandweb.com/texturepacker",
		"version": "3.0",
		"smartupdate": "$TexturePacker:SmartUpdate:8b0b336cae3df719367dac0e9c637e96:3dd52194c0bc86ca8d350f0a9f5e2628:bfa545a7ffa5cc0d812cb9ab56dcf146$"
	}
}
